[
  {
    "type": "",
    "title": "Basic",
    "pricing": "0",
    "pricingUnit": "$",
    "popular": false,
    "features": [
      {
        "name": "Unlimited chat with AI",
        "isIncluded": true
      },
      {
        "name": "3 connections per week",
        "isIncluded": true
      },
      {
        "name": "Fast AI only",
        "isIncluded": true
      }
    ],
    "button": "Try it Now"
  },
  {
    "type": "wk",
    "title": "Premium",
    "pricing": "2",
    "pricingUnit": "$",
    "popular": true,
    "features": [
      {
        "name": "Unlimited chat with AI",
        "isIncluded": true
      },
      {
        "name": "10 connections per week",
        "isIncluded": true
      },
      {
        "name": "High-quality AI",
        "isIncluded": true
      }
    ],
    "button": "Most Popular"
  },
  {
    "type": "wk",
    "title": "Unlimited",
    "pricing": "5",
    "pricingUnit": "$",
    "popular": true,
    "features": [
      {
        "name": "Unlimited chat with AI",
        "isIncluded": true
      },
      {
        "name": "Unlimited connections",
        "isIncluded": true
      },
      {
        "name": "Highest-quality AI",
        "isIncluded": true
      }
    ],
    "button": "Best Experience"
  }
]
